fragannot/__init__.py
fragannot/_version.py
fragannot/constant.py
fragannot/fragannot.py
fragannot/log_conf.json
fragannot/parser.py
fragannot/spectrumfile.py
fragannot/temp.py
fragannot-0.13.dist-info/METADATA
fragannot-0.13.dist-info/WHEEL
fragannot-0.13.dist-info/entry_points.txt
fragannot-0.13.dist-info/top_level.txt
fragannot-0.13.dist-info/RECORD
