Metadata-Version: 2.1
Name: fragannot
Version: 0.13
Summary: A python CLI app for fragment annotation
Home-page: 
Author: eubic ms 2023 hackathon team (to update)
Author-email: 
License: UNKNOWN
Platform: UNKNOWN
Classifier: Programming Language :: Python :: 3.8
Requires-Dist: numpy
Requires-Dist: pyteomics
Requires-Dist: argparse
Requires-Dist: pprintpp
Requires-Dist: spectrum-utils
Requires-Dist: psm-utils
